einmind/__init__.py
einmind/api_handler.py
einmind/icd10cm/__init__.py
einmind/icd10cm/icd10cm_client.py
einmind/icd10cm/schemas.py
einmind/snomed_ct/__init__.py
einmind/snomed_ct/schemas.py
einmind/snomed_ct/snomed_ct_client.py
einmind-0.1.21.dist-info/METADATA
einmind-0.1.21.dist-info/WHEEL
einmind-0.1.21.dist-info/licenses/LICENSE
einmind-0.1.21.dist-info/licenses/NOTICE
einmind-0.1.21.dist-info/RECORD
