Metadata-Version: 2.3
Name: einmind
Version: 0.1.21
Summary: EinMind SDK for Python
Project-URL: Homepage, https://github.com/einmind/einmind_client
Project-URL: Documentation, https://docs.einmind.com/
Project-URL: Bug Tracker, https://github.com/einmind/einmind_client/issues
Project-URL: Discussions, https://github.com/einmind/einmind_client/discussions
Project-URL: Changelog, https://docs.einmind.com/latest/changelog
License-Expression: Apache-2.0
License-File: LICENSE
License-File: NOTICE
Keywords: auto-coding,einmind,icd 10,icd-10-cm,icd10,icd10cm,meddra,medical coding,snomed,snomed ct,snomed-ct
Classifier: Development Status :: 4 - Beta
Classifier: License :: OSI Approved :: Apache Software License
Classifier: Programming Language :: Python :: 3 :: Only
Classifier: Programming Language :: Python :: 3.7
Classifier: Programming Language :: Python :: 3.8
Classifier: Programming Language :: Python :: 3.9
Classifier: Programming Language :: Python :: 3.10
Classifier: Programming Language :: Python :: 3.11
Classifier: Programming Language :: Python :: 3.12
Classifier: Topic :: Scientific/Engineering :: Physics
Requires-Python: >=3.7
Requires-Dist: pydantic>=2.5.3
Requires-Dist: requests
Requires-Dist: urllib3>=2.0.7
